snapintime/__init__.py
snapintime/create_local_snapshots.py
snapintime/culling.py
snapintime/remote_backup.py
snapintime/remote_culling.py
snapintime/tests/__init__.py
snapintime/tests/test_create_local_snapshots.py
snapintime/tests/test_culling.py
snapintime/tests/test_remote_backup.py
snapintime/utils/__init__.py
snapintime/utils/config.py
snapintime/utils/date.py
snapintime/utils/tests/__init__.py
snapintime/utils/tests/test_time.py
snapintime-2.2.2.dist-info/LICENSE
snapintime-2.2.2.dist-info/METADATA
snapintime-2.2.2.dist-info/WHEEL
snapintime-2.2.2.dist-info/top_level.txt
snapintime-2.2.2.dist-info/RECORD
