Metadata-Version: 2.1
Name: snapintime
Version: 2.2.2
Summary: A program for creating, culling, and remote backup of btrfs snapshots
Home-page: https://github.com/djotaku/Snap-in-Time
Author: Eric Mesa
Author-email: eric@ericmesa.com
License: GPLv3
Keywords: btrfs
Classifier: Intended Audience :: End Users/Desktop
Classifier: License :: OSI Approved :: GNU General Public License v3 (GPLv3)
Classifier: Programming Language :: Python :: 3
License-File: LICENSE
Requires-Dist: xdgenvpy==2.4.0
Requires-Dist: rich==13.7.1
